{
  "canisters": {
    "token": {
      "type": "motoko",
      "main": "src/backend/token/main.mo"
    },
    "nft": {
      "type": "motoko",
      "main": "src/backend/nft/main.mo"
    },
    "marketplace": {
      "type": "motoko",
      "main": "src/backend/marketplace/main.mo"
    },
    "staking": {
      "type": "motoko",
      "main": "src/backend/staking/main.mo"
    },
    "dao": {
      "type": "motoko",
      "main": "src/backend/dao/main.mo"
    }
  },
  "defaults": {
    "build": {
      "args": "",
      "packtool": ""
    }
  },
  "dfx": "0.11.0",
  "networks": {
    "local": {
      "bind": "127.0.0.1:8000",
      "type": "ephemeral"
    }
  },
  "version": 1
}
